<?xml version="1.0" encoding="UTF-8" standalone="yes"?>
<autorizacion>
<estado>AUTORIZADO</estado>
<numeroAutorizacion>2910202501179222137400120010050000206774388955017</numeroAutorizacion>
<fechaAutorizacion>2025-10-29T16:31:47-05:00</fechaAutorizacion>
<ambiente>PRODUCCIÓN</ambiente>
<comprobante><![CDATA[<?xml version="1.0" encoding="UTF-8"?><factura id="comprobante" version="2.1.0">
	<infoTributaria>
		<ambiente>2</ambiente>
	    <tipoEmision>1</tipoEmision>
	    <razonSocial>BUSINESS MANUFACTURING COMPANY DEL ECUADOR S.A. BUSINESSMANUFACT</razonSocial>
	    <nombreComercial>BUSINESS MANUFACTURING COMPANY DEL ECUADOR S.A. BUSINESSMANUFACT</nombreComercial>
	    <ruc>1792221374001</ruc>
	    <claveAcceso>2910202501179222137400120010050000206774388955017</claveAcceso>
	    <codDoc>01</codDoc>
	    <estab>001</estab>
	    <ptoEmi>005</ptoEmi>
	    <secuencial>000020677</secuencial>
	    <dirMatriz>IÑAQUITO / EL DIA 357 Y EL MERCURIO.</dirMatriz>
		
		
			<agenteRetencion>1</agenteRetencion>
		
		
  	</infoTributaria>
	<infoFactura>
	    <fechaEmision>29/10/2025</fechaEmision>
		
			<dirEstablecimiento>IÑAQUITO / EL DIA 357 Y EL MERCURIO.</dirEstablecimiento>
		
	    
	    
			<obligadoContabilidad>SI</obligadoContabilidad>
		
		
	    
	    <tipoIdentificacionComprador>04</tipoIdentificacionComprador>
		
		<razonSocialComprador>BARCIA DELGADO JENNY GERMANIA</razonSocialComprador>
	    <identificacionComprador>1302177611001</identificacionComprador>
		<direccionComprador>CALLE 16 B ENTRE 12VA Y CALLE 18 - DIAGONAL HOSPITAL DE MANTA CENTER</direccionComprador>
	    
	    <totalSinImpuestos>254.00000</totalSinImpuestos>
		
	  	
	    <totalDescuento>25.40</totalDescuento>
	    
	    <totalConImpuestos>
		
			
			<totalImpuesto>
				<codigo>2</codigo>
				<codigoPorcentaje>4</codigoPorcentaje>
				<descuentoAdicional>0</descuentoAdicional>
				<baseImponible>0.00</baseImponible>
				<valor>0.00000</valor>
			</totalImpuesto>
			
			
			<totalImpuesto>
				<codigo>2</codigo>
				<codigoPorcentaje>5</codigoPorcentaje>
				<descuentoAdicional>0</descuentoAdicional>
				<baseImponible>0</baseImponible>
				<valor>0.00</valor>
			</totalImpuesto>
			
		
			      
			<totalImpuesto>
				<codigo>2</codigo>
				<codigoPorcentaje>0</codigoPorcentaje>
				<descuentoAdicional>0</descuentoAdicional>
				<baseImponible>254.00000</baseImponible>
				<valor>0</valor>
			</totalImpuesto>
		
	      
		  
		  
	    </totalConImpuestos>
	    <propina>0</propina>
	    <importeTotal>254.00000</importeTotal>
	    <moneda>DOLAR</moneda>
		
	    
	    <pagos>
	    	
	    	<pago>
	    		<formaPago>20</formaPago>
	    		<total>254.00</total>
	    		<plazo>0</plazo>
	    		<unidadTiempo>días</unidadTiempo>
	    	</pago>
	    	
	    </pagos>
	    
  	</infoFactura>
  	<detalles>
  	
    <detalle>
      
      	<codigoPrincipal>300058</codigoPrincipal>
		<codigoAuxiliar>654.0</codigoAuxiliar>
      	<descripcion>Fórmula Magistral Cápsulas Minoxidil 2.5mg</descripcion>
      
      <cantidad>7.000000</cantidad>
      <precioUnitario>12.100000</precioUnitario>
	  
      <descuento>0.00</descuento>
      <precioTotalSinImpuesto>84.70</precioTotalSinImpuesto>
	  
	  
	  	<detallesAdicionales>
			
    			<detAdicional nombre="Lote" valor="C2510008"/>
    		
    			<detAdicional nombre="Exp." valor="06/10/2026"/>
    		
      	</detallesAdicionales>
      
            
      
      <impuestos>
        <impuesto>
          <codigo>2</codigo>
          <codigoPorcentaje>0</codigoPorcentaje>
          <tarifa>0</tarifa>
          <baseImponible>84.70000</baseImponible>
          <valor>0.00</valor>
        </impuesto>
        
		
		
      </impuestos>
	  
	</detalle>
    
    <detalle>
      
      	<codigoPrincipal>300058</codigoPrincipal>
		<codigoAuxiliar>654.0</codigoAuxiliar>
      	<descripcion>Fórmula Magistral Cápsulas Minoxidil 2.5mg</descripcion>
      
      <cantidad>1.000000</cantidad>
      <precioUnitario>12.100000</precioUnitario>
	  
      <descuento>12.10</descuento>
      <precioTotalSinImpuesto>0.00</precioTotalSinImpuesto>
	  
	  
	  	<detallesAdicionales>
			
    			<detAdicional nombre="Lote" valor="C2510008"/>
    		
    			<detAdicional nombre="Exp." valor="02/10/2026"/>
    		
      	</detallesAdicionales>
      
            
      
      <impuestos>
        <impuesto>
          <codigo>2</codigo>
          <codigoPorcentaje>0</codigoPorcentaje>
          <tarifa>0</tarifa>
          <baseImponible>0.00000</baseImponible>
          <valor>0.00</valor>
        </impuesto>
        
		
		
      </impuestos>
	  
	</detalle>
    
    <detalle>
      
      	<codigoPrincipal>300058</codigoPrincipal>
		<codigoAuxiliar>654.0</codigoAuxiliar>
      	<descripcion>Fórmula Magistral Cápsulas Minoxidil 2.5mg</descripcion>
      
      <cantidad>3.000000</cantidad>
      <precioUnitario>12.100000</precioUnitario>
	  
      <descuento>0.00</descuento>
      <precioTotalSinImpuesto>36.30</precioTotalSinImpuesto>
	  
	  
	  	<detallesAdicionales>
			
    			<detAdicional nombre="Lote" valor="C2510087"/>
    		
    			<detAdicional nombre="Exp." valor="17/10/2026"/>
    		
      	</detallesAdicionales>
      
            
      
      <impuestos>
        <impuesto>
          <codigo>2</codigo>
          <codigoPorcentaje>0</codigoPorcentaje>
          <tarifa>0</tarifa>
          <baseImponible>36.30000</baseImponible>
          <valor>0.00</valor>
        </impuesto>
        
		
		
      </impuestos>
	  
	</detalle>
    
    <detalle>
      
      	<codigoPrincipal>300095</codigoPrincipal>
		<codigoAuxiliar>108896.0</codigoAuxiliar>
      	<descripcion>Fórmula Magistral Cápsulas Minoxidil Forte 5mg</descripcion>
      
      <cantidad>10.000000</cantidad>
      <precioUnitario>13.300000</precioUnitario>
	  
      <descuento>0.00</descuento>
      <precioTotalSinImpuesto>133.00</precioTotalSinImpuesto>
	  
	  
	  	<detallesAdicionales>
			
    			<detAdicional nombre="Lote" valor="C2510131"/>
    		
    			<detAdicional nombre="Exp." valor="28/10/2026"/>
    		
      	</detallesAdicionales>
      
            
      
      <impuestos>
        <impuesto>
          <codigo>2</codigo>
          <codigoPorcentaje>0</codigoPorcentaje>
          <tarifa>0</tarifa>
          <baseImponible>133.00000</baseImponible>
          <valor>0.00</valor>
        </impuesto>
        
		
		
      </impuestos>
	  
	</detalle>
    
    <detalle>
      
      	<codigoPrincipal>300095</codigoPrincipal>
		<codigoAuxiliar>108896.0</codigoAuxiliar>
      	<descripcion>Fórmula Magistral Cápsulas Minoxidil Forte 5mg</descripcion>
      
      <cantidad>1.000000</cantidad>
      <precioUnitario>13.300000</precioUnitario>
	  
      <descuento>13.30</descuento>
      <precioTotalSinImpuesto>0.00</precioTotalSinImpuesto>
	  
	  
	  	<detallesAdicionales>
			
    			<detAdicional nombre="Lote" valor="C2510131"/>
    		
    			<detAdicional nombre="Exp." valor="28/10/2026"/>
    		
      	</detallesAdicionales>
      
            
      
      <impuestos>
        <impuesto>
          <codigo>2</codigo>
          <codigoPorcentaje>0</codigoPorcentaje>
          <tarifa>0</tarifa>
          <baseImponible>0.00000</baseImponible>
          <valor>0.00</valor>
        </impuesto>
        
		
		
      </impuestos>
	  
	</detalle>
    
	
	
	
    </detalles>
    
	
    
    <infoAdicional>
    	
    		
    			<campoAdicional nombre="Descripción">-.</campoAdicional>
    		
    	
		
    </infoAdicional>
	
	
<ds:Signature xmlns:ds="http://www.w3.org/2000/09/xmldsig#" xmlns:etsi="http://uri.etsi.org/01903/v1.3.2#" Id="Signature777227">
<ds:SignedInfo Id="Signature-SignedInfo786430">
<ds:CanonicalizationMethod Algorithm="http://www.w3.org/TR/2001/REC-xml-c14n-20010315"/>
<ds:SignatureMethod Algorithm="http://www.w3.org/2000/09/xmldsig#rsa-sha1"/>
<ds:Reference Id="SignedPropertiesID735274" Type="http://uri.etsi.org/01903#SignedProperties" URI="#Signature777227-SignedProperties223746">
<ds:DigestMethod Algorithm="http://www.w3.org/2000/09/xmldsig#sha1"/>
<ds:DigestValue>bUoMKxRTPzr+lXntZsuOPwUHyZ0=</ds:DigestValue>
</ds:Reference>
<ds:Reference URI="#Certificate648042">
<ds:DigestMethod Algorithm="http://www.w3.org/2000/09/xmldsig#sha1"/>
<ds:DigestValue>kuLRt1pELBqBKq+bQRoc4wHZ5GU=</ds:DigestValue>
</ds:Reference>
<ds:Reference Id="Reference-ID-582538" URI="#comprobante">
<ds:Transforms>
<ds:Transform Algorithm="http://www.w3.org/2000/09/xmldsig#enveloped-signature"/>
</ds:Transforms>
<ds:DigestMethod Algorithm="http://www.w3.org/2000/09/xmldsig#sha1"/>
<ds:DigestValue>kbSk/hMi0ytIskridznPX9ELoKY=</ds:DigestValue>
</ds:Reference>
</ds:SignedInfo>
<ds:SignatureValue Id="SignatureValue253529">
yj+8JvFwaz1PWwffvnGTVV+BhIZOL+Al1B/taxAw9r9ReNNFVNzc5rOCJhLQPGWXh2TnVLxlKCN+
JWOxnS2cQNH1TrRu6O7S8KK6RF2DVJw4S2/26Dg7L1JMxkuiOiadF9LwubXi0n1wJRb4Jdrk4qbD
7eVO8swVafmpa66ZeF0yOcbFnYCfSp1CCLDseo0mhIED5jI79fJtdEfXRb2ZuzZq21AmK+eVnuYT
GlKjfovemnl61bPe2HEK/lOQjNMmY1ed/6mn4N0NOq0FjUPdzkgAn9JFPaTMNmR/7evi2DmtRzT3
8lm7XblCXTdDBJYA3mH5pLaPUVoI7YjOx0YxmA==
</ds:SignatureValue>
<ds:KeyInfo Id="Certificate648042">
<ds:X509Data>
<ds:X509Certificate>
MIIMojCCCoqgAwIBAgIEWOG5ajANBgkqhkiG9w0BAQsFADCBmTELMAkGA1UEBhMCRUMxHTAbBgNV
BAoMFFNFQ1VSSVRZIERBVEEgUy5BLiAyMTAwLgYDVQQLDCdFTlRJREFEIERFIENFUlRJRklDQUNJ
T04gREUgSU5GT1JNQUNJT04xOTA3BgNVBAMMMEFVVE9SSURBRCBERSBDRVJUSUZJQ0FDSU9OIFNV
QkNBLTIgU0VDVVJJVFkgREFUQTAeFw0yNDA2MjcxNzU4MDhaFw0yNzA2MjcxNzU4MDhaMIGxMS8w
LQYDVQQDDCZNQVJJQSBERSBMT1MgQU5HRUxFUyBGUkVJUkUgQUxUQU1JUkFOTzEgMB4GA1UEBRMX
MTcwOTcwNzczOS0yNzA2MjQxMzA3NTMxMDAuBgNVBAsMJ0VOVElEQUQgREUgQ0VSVElGSUNBQ0lP
TiBERSBJTkZPUk1BQ0lPTjEdMBsGA1UECgwUU0VDVVJJVFkgREFUQSBTLkEuIDIxCzAJBgNVBAYT
AkVDMIIBIjANBgkqhkiG9w0BAQEFAAOCAQ8AMIIBCgKCAQEA0N2LZXijhQHkcZ48RQOcCi0EP+u+
KqhBqLlAbk62n4fkXSJN7BKGcZOgMHaFQ/cqqF+bPGpYW685gUqoiXUofi1p5eYu45zEydemjKHQ
G+OCTKPk2IFwCNCeeAblhWgh6WjcVIsjL8F0kNCpwGYbCUx1oCkLtTP4cmLWfjpiVWiIMeZaikYu
NHBfaZ6+2a9CmEaVt69Axs8XIFcXO2NznvaaBAu/uoC4KfuUzBFEyhP9FkrZYXCQldcJSfZuC7Ul
ih26K+FfeXTMmww7dse3Dt/n4S9xbYkHoNlgz2btPAUDAhRiFejY5rh6lCvSDIweT3CQMFfrQIGe
NUZ3uAF3DwIDAQABo4IH1jCCB9IwDAYDVR0TAQH/BAIwADAfBgNVHSMEGDAWgBSMusoRV3glgB1r
CktVv42uYt29jzBZBggrBgEFBQcBAQRNMEswSQYIKwYBBQUHMAGGPWh0dHA6Ly9vY3NwZ3cuc2Vj
dXJpdHlkYXRhLm5ldC5lYy9lamJjYS9wdWJsaWN3ZWIvc3RhdHVzL29jc3Awgc8GA1UdLgSBxzCB
xDCBwaCBvqCBu4aBuGxkYXA6Ly9sZGFwc2RjYTIuc2VjdXJpdHlkYXRhLm5ldC5lYy9DTj1BVVRP
UklEQUQgREUgQ0VSVElGSUNBQ0lPTiBTVUJDQS0yIFNFQ1VSSVRZIERBVEEsT1U9RU5USURBRCBE
RSBDRVJUSUZJQ0FDSU9OIERFIElORk9STUFDSU9OLE89U0VDVVJJVFkgREFUQSBTLkEuIDIsQz1F
Qz9kZWx0YVJldm9jYXRpb25MaXN0P2Jhc2UwJwYDVR0RBCAwHoEcZmluYW5jaWVyb0BibWNkZWxl
Y3VhZG9yLmNvbTCCARUGA1UdIASCAQwwggEIMGIGCisGAQQBgqZyAgkwVDBSBggrBgEFBQcCAjBG
HkQAQwBlAHIAdABpAGYAaQBjAGEAZABvACAAZABlACAAUgBlAHAAcgBlAHMAZQBuAHQAYQBuAHQA
ZQAgAEwAZQBnAGEAbDCBoQYKKwYBBAGCpnICAzCBkjCBjwYIKwYBBQUHAgEWgYJodHRwczovL3d3
dy5zZWN1cml0eWRhdGEubmV0LmVjL3dwLWNvbnRlbnQvZG93bmxvYWRzL05vcm1hdGl2YXMvUF9k
ZV9DZXJ0aWZpY2Fkb3MvUG9saXRpY2FzIGRlIENlcnRpZmljYWRvIFJlcHJlc2VudGFudGUgTGVn
YWwucGRmMIICogYDVR0fBIICmTCCApUwgeWgQaA/hj1odHRwOi8vb2NzcGd3LnNlY3VyaXR5ZGF0
YS5uZXQuZWMvZWpiY2EvcHVibGljd2ViL3N0YXR1cy9vY3NwooGfpIGcMIGZMTkwNwYDVQQDDDBB
VVRPUklEQUQgREUgQ0VSVElGSUNBQ0lPTiBTVUJDQS0yIFNFQ1VSSVRZIERBVEExMDAuBgNVBAsM
J0VOVElEQUQgREUgQ0VSVElGSUNBQ0lPTiBERSBJTkZPUk1BQ0lPTjEdMBsGA1UECgwUU0VDVVJJ
VFkgREFUQSBTLkEuIDIxCzAJBgNVBAYTAkVDMIHHoIHEoIHBhoG+bGRhcDovL2xkYXBzZGNhMi5z
ZWN1cml0eWRhdGEubmV0LmVjL0NOPUFVVE9SSURBRCBERSBDRVJUSUZJQ0FDSU9OIFNVQkNBLTIg
U0VDVVJJVFkgREFUQSxPVT1FTlRJREFEIERFIENFUlRJRklDQUNJT04gREUgSU5GT1JNQUNJT04s
Tz1TRUNVUklUWSBEQVRBIFMuQS4gMixDPUVDP2NlcnRpZmljYXRlUmV2b2NhdGlvbkxpc3Q/YmFz
ZTCB4KCB3aCB2oaB12h0dHBzOi8vcG9ydGFsLW9wZXJhZG9yMi5zZWN1cml0eWRhdGEubmV0LmVj
L2VqYmNhL3B1YmxpY3dlYi93ZWJkaXN0L2NlcnRkaXN0P2NtZD1jcmwmaXNzdWVyPUNOPUFVVE9S
SURBRCBERSBDRVJUSUZJQ0FDSU9OIFNVQkNBLTIgU0VDVVJJVFkgREFUQSxPVT1FTlRJREFEIERF
IENFUlRJRklDQUNJT04gREUgSU5GT1JNQUNJT04sTz1TRUNVUklUWSBEQVRBIFMuQS4gMixDPUVD
MB0GA1UdDgQWBBSdd5UQPPPWGQprigjSW79Ct6yIKTArBgNVHRAEJDAigA8yMDI0MDYyNzE3NTgw
OFqBDzIwMjcwNjI3MTc1ODA4WjALBgNVHQ8EBAMCBeAwHwYKKwYBBAGCpnIDBQQRDA9HRVJFTlRF
IEdFTkVSQUwwGgYKKwYBBAGCpnIDAQQMDAoxNzA5NzA3NzM5MG8GCisGAQQBgqZyAwkEYQxfUVVJ
VE8gRElTVFJJVE8gTUVUUk9QT0xJVEFOTyBDQUJFQ0VSQSBDQU5UT05BTCBDQVBJVEFMIFBST1ZJ
TkNJQUwgWSBERSBMQSBSRVBVQkxJQ0EgREVMIEVDVUFET1IwEQYKKwYBBAGCpnIDIgQDDAEuMCgG
CisGAQQBgqZyAwcEGgwYRUwgRElBIDM1NyBZIEVMIE1FUkNVUklPMCQGCisGAQQBgqZyAwIEFgwU
TUFSSUEgREUgTE9TIEFOR0VMRVMwHwYKKwYBBAGCpnIDIAQRDA8wMDQwMDEwMDAxMDgyMjUwEwYK
KwYBBAGCpnIDIQQFDANQRlgwFwYKKwYBBAGCpnIDDAQJDAdFQ1VBRE9SMBYGCisGAQQBgqZyAwME
CAwGRlJFSVJFME8GCisGAQQBgqZyAwoEQQw/QlVTSU5FU1MgTUFOVUZBQ1RVUklORyBDT01QQU5Z
IERFTCBFQ1VBRE9SIFMgQSBCVVNJTkVTU01BTlVGQUNUMB0GCisGAQQBgqZyAwsEDwwNMTc5MjIy
MTM3NDAwMTARBgorBgEEAYKmcgMdBAMMAS4wGgYKKwYBBAGCpnIDBAQMDApBTFRBTUlSQU5PMBwG
CisGAQQBgqZyAwgEDgwMNTkzOTk4NTIxMTAyMA0GCSqGSIb3DQEBCwUAA4ICAQC7Ed2t6ZXT8zWt
hPAwyUHPhL3gOAXlgy+Sg0zRlUO6eMPqJ5Xu4royUgluH1uQN8sv8U4gmGhIKvUIgeupQWLpjJEh
23SK74OxNdCBcEYl8gSdpC+xMjenSUA+UkSQMB7KJebu80R6XWnI9WdITmhPMyAO7R5igyqrAU5Q
R65Z+eCHizVkR29DikkK/GZb4guPJBJOUluiB1Ztz17YU+eFPt+2QrzRhF7VrjrmRCuTNGLD46r9
PIq/hVZmG/BUB5Dw05zTaW/tdmD3otiQyjRlcsUW7muhM9rI0yJEWd5SAm229BZ4Tb5PRIvg6PGv
HNnCJE3sTYBh/BNKb3+akJxJkvKetjaYmpGjHvc+gwpYAvpnnH+bY77ELFFJ4m91M1Ky8uwbIO42
QhO6DwPpJa9Znfby5JxpwMcZKPs4r67I3blC525e8h8kFRIWHEGPyBZI2omZhedKb5uB8UX5RJ6R
ctGh14GP/N7kiDxlXXuQ/7zvpzwchemApdXPdzdQUmBDcz4DYbob7ibXNQ486c0slMXT6g6vdsZ6
kMjtbXYY349zS3BiSRPB8IKATxJayk1uk7Y28jy6EA0DP2K+jpq09Sziqrza+ad2pcbKTNsHaH0p
Xfafx4qSKfLN4poaAlyyOibHnXHA6Khx/oV0r+wEdHHKT85HXX+0XnbCuNdvbA==
</ds:X509Certificate>
</ds:X509Data>
<ds:KeyValue>
<ds:RSAKeyValue>
<ds:Modulus>
0N2LZXijhQHkcZ48RQOcCi0EP+u+KqhBqLlAbk62n4fkXSJN7BKGcZOgMHaFQ/cqqF+bPGpYW685
gUqoiXUofi1p5eYu45zEydemjKHQG+OCTKPk2IFwCNCeeAblhWgh6WjcVIsjL8F0kNCpwGYbCUx1
oCkLtTP4cmLWfjpiVWiIMeZaikYuNHBfaZ6+2a9CmEaVt69Axs8XIFcXO2NznvaaBAu/uoC4KfuU
zBFEyhP9FkrZYXCQldcJSfZuC7Ulih26K+FfeXTMmww7dse3Dt/n4S9xbYkHoNlgz2btPAUDAhRi
FejY5rh6lCvSDIweT3CQMFfrQIGeNUZ3uAF3Dw==
</ds:Modulus>
<ds:Exponent>AQAB</ds:Exponent>
</ds:RSAKeyValue>
</ds:KeyValue>
</ds:KeyInfo>
<ds:Object Id="Signature777227-Object28821"><etsi:QualifyingProperties Target="#Signature777227"><etsi:SignedProperties Id="Signature777227-SignedProperties223746"><etsi:SignedSignatureProperties><etsi:SigningTime>2025-10-29T16:31:45-05:00</etsi:SigningTime><etsi:SigningCertificate><etsi:Cert><etsi:CertDigest><ds:DigestMethod Algorithm="http://www.w3.org/2000/09/xmldsig#sha1"/><ds:DigestValue>VEGbHlDvSWpIDq/iERsDikjm9NY=</ds:DigestValue></etsi:CertDigest><etsi:IssuerSerial><ds:X509IssuerName>CN=AUTORIDAD DE CERTIFICACION SUBCA-2 SECURITY DATA,C=EC,O=SECURITY DATA S.A. 2,OU=ENTIDAD DE CERTIFICACION DE INFORMACION</ds:X509IssuerName><ds:X509SerialNumber>1491188074</ds:X509SerialNumber></etsi:IssuerSerial></etsi:Cert></etsi:SigningCertificate></etsi:SignedSignatureProperties></etsi:SignedProperties></etsi:QualifyingProperties></ds:Object></ds:Signature></factura>]]></comprobante>
<mensajes/>
</autorizacion>

